__init__.py
main.py
jsend2/__init__.py
jsend2/django/__init__.py
jsend2/django/apps.py
jsend2/django/exception.py
jsend2/django/utils.py
jsend2/jfast/__init__.py
jsend2/jfast/exception.py
jsend2/jfast/pagination.py
jsend2/jfast/response.py
jsend2-0.0.8.dist-info/METADATA
jsend2-0.0.8.dist-info/WHEEL
jsend2-0.0.8.dist-info/top_level.txt
jsend2-0.0.8.dist-info/RECORD
