Metadata-Version: 2.1
Name: jsend2
Version: 0.0.8
Author-email: Mohammadreza ZOLGHADRI <zolghadri1999@email.com>, Amirreza Taherkhani <amirrezataherkhaani@gmail.com>
Keywords: fastapi,django,jsend
Classifier: Programming Language :: Python :: 3
Classifier: Operating System :: POSIX :: Linux
Requires-Python: >=3.9
Requires-Dist: fastapi
Requires-Dist: pydantic
Requires-Dist: django
Requires-Dist: fastapi-pagination
